core/__init__.py
core/client_flask_img.py
core/infer.py
core/infer_label.py
core/mq_write.py
core/oss_upload_img.py
core/pic_snapshots.py
core/send_email.py
core/send_msg.py
core/server_ai_xunjian.py
smart_sync-0.0.3.dist-info/LICENSE
smart_sync-0.0.3.dist-info/METADATA
smart_sync-0.0.3.dist-info/WHEEL
smart_sync-0.0.3.dist-info/top_level.txt
smart_sync-0.0.3.dist-info/RECORD
