Metadata-Version: 2.1
Name: smart-sync
Version: 0.0.3
Summary: smart AI detection project of sync.
Home-page: https://github.com/lvboodvl/smart_sync.git
Author: Bo Lv
Author-email: fengdieer_13@126.com
License: MIT
Platform: UNKNOWN
Classifier: License :: OSI Approved :: MIT License
Classifier: Programming Language :: Python
Classifier: Programming Language :: Python :: 3
Classifier: Programming Language :: Python :: 3.6
Classifier: Programming Language :: Python :: Implementation :: CPython
Classifier: Programming Language :: Python :: Implementation :: PyPy
Requires-Python: >=3.6.0
Requires-Dist: Flask (>=1.1.2)
Requires-Dist: ipython (>=7.15.0)
Requires-Dist: numpy (>=1.18.4)
Requires-Dist: oss2 (>=2.12.1)
Requires-Dist: requests (>=2.23.0)
Requires-Dist: aliyun-python-sdk-core (>=2.13.23)
